var kios = {
"type": "FeatureCollection",
"name": "layer_kios",
"crs": { "type": "name", "properties": { "name": "urn:ogc:def:crs:OGC:1.3:CRS84" } },
"features": [
{ "type": "Feature", "properties": { "Id": 1, "Kios": null, "penanggung": null }, "geometry": { "type": "Point", "coordinates": [ 107.205170967224305, -6.732643109369463 ] } },
{ "type": "Feature", "properties": { "Id": 2, "Kios": null, "penanggung": null }, "geometry": { "type": "Point", "coordinates": [ 107.151093131915914, -6.676198660713371 ] } },
{ "type": "Feature", "properties": { "Id": 3, "Kios": null, "penanggung": null }, "geometry": { "type": "Point", "coordinates": [ 107.202848387735443, -6.694984110867563 ] } },
{ "type": "Feature", "properties": { "Id": 4, "Kios": null, "penanggung": null }, "geometry": { "type": "Point", "coordinates": [ 107.235892838183702, -6.702009827744891 ] } },
{ "type": "Feature", "properties": { "Id": 5, "Kios": null, "penanggung": null }, "geometry": { "type": "Point", "coordinates": [ 107.260920796839883, -6.786778467291068 ] } },
{ "type": "Feature", "properties": { "Id": 6, "Kios": null, "penanggung": null }, "geometry": { "type": "Point", "coordinates": [ 107.276815759681412, -6.791743562939652 ] } },
{ "type": "Feature", "properties": { "Id": 7, "Kios": null, "penanggung": null }, "geometry": { "type": "Point", "coordinates": [ 107.248217696661044, -6.816092415766343 ] } },
{ "type": "Feature", "properties": { "Id": 8, "Kios": null, "penanggung": null }, "geometry": { "type": "Point", "coordinates": [ 107.203640580210049, -6.813607298114875 ] } },
{ "type": "Feature", "properties": { "Id": 9, "Kios": null, "penanggung": null }, "geometry": { "type": "Point", "coordinates": [ 107.204125966671654, -6.785581202773077 ] } },
{ "type": "Feature", "properties": { "Id": 10, "Kios": null, "penanggung": null }, "geometry": { "type": "Point", "coordinates": [ 107.160663877136543, -6.793956683438026 ] } },
{ "type": "Feature", "properties": { "Id": 11, "Kios": null, "penanggung": null }, "geometry": { "type": "Point", "coordinates": [ 107.156252411455128, -6.802730252508906 ] } },
{ "type": "Feature", "properties": { "Id": 12, "Kios": null, "penanggung": null }, "geometry": { "type": "Point", "coordinates": [ 107.188189692249424, -6.785366375625666 ] } },
{ "type": "Feature", "properties": { "Id": 13, "Kios": null, "penanggung": null }, "geometry": { "type": "Point", "coordinates": [ 107.038688302638349, -7.382368758429367 ] } },
{ "type": "Feature", "properties": { "Id": 14, "Kios": null, "penanggung": null }, "geometry": { "type": "Point", "coordinates": [ 106.98178049986835, -7.382026980922502 ] } },
{ "type": "Feature", "properties": { "Id": 15, "Kios": null, "penanggung": null }, "geometry": { "type": "Point", "coordinates": [ 107.006338427874738, -7.381618317336721 ] } },
{ "type": "Feature", "properties": { "Id": 16, "Kios": null, "penanggung": null }, "geometry": { "type": "Point", "coordinates": [ 107.014837639100449, -7.340319120057191 ] } },
{ "type": "Feature", "properties": { "Id": 17, "Kios": null, "penanggung": null }, "geometry": { "type": "Point", "coordinates": [ 107.062270168428014, -7.30033887523344 ] } },
{ "type": "Feature", "properties": { "Id": 18, "Kios": null, "penanggung": null }, "geometry": { "type": "Point", "coordinates": [ 107.009913419637499, -7.310740830875055 ] } }
]
}
